notebookllm/__init__.py
notebookllm/notebookllm.py
notebookllm-1.1.0.dist-info/METADATA
notebookllm-1.1.0.dist-info/WHEEL
notebookllm-1.1.0.dist-info/entry_points.txt
notebookllm-1.1.0.dist-info/top_level.txt
notebookllm-1.1.0.dist-info/RECORD
