Metadata-Version: 2.4
Name: notebookllm
Version: 1.1.0
Summary: A tool for converting Jupyter notebooks to interactive LLM-friendly and token efficient formats by providing CLI utilities for notebook management and processing.
Author-email: Yasir Raza <yasirabdali6@gmail.com>
Keywords: jupyter,notebook,llm,conversion,mcp,cli
Requires-Python: >=3.10
Requires-Dist: nbformat
Requires-Dist: jupyter_client
